pythonix/__init__.py
pythonix/collections.py
pythonix/crumb.py
pythonix/curry.py
pythonix/fn.py
pythonix/grammar.py
pythonix/internals/__init__.py
pythonix/internals/collections.py
pythonix/internals/crumb.py
pythonix/internals/curry.py
pythonix/internals/fn.py
pythonix/internals/grammar.py
pythonix/internals/prove.py
pythonix/internals/res.py
pythonix/internals/traits.py
pythonix/internals/utils.py
pythonix/prelude.py
pythonix/prove.py
pythonix/res.py
pythonix/traits.py
pythonix/utils.py
pythonix-3.0.0.dist-info/LICENSE
pythonix-3.0.0.dist-info/METADATA
pythonix-3.0.0.dist-info/WHEEL
pythonix-3.0.0.dist-info/RECORD
