Metadata-Version: 2.1
Name: pythonix
Version: 3.0.0
Summary: Rust and Gleam like functional programming in Python, complete with Results, pipes, and currying, log traililng, and so much more
Home-page: https://github.com/jhok2013/pythonix
License: Apache-2.0
Keywords: functional,pipes,result,error-as-values,Rust,Gleam,logging
Author: jhok2013
Author-email: jhok2013@gmail.com
Requires-Python: >=3.10,<4.0
Classifier: License :: OSI Approved :: Apache Software License
Classifier: Programming Language :: Python :: 3
Classifier: Programming Language :: Python :: 3.10
Classifier: Programming Language :: Python :: 3.11
Classifier: Programming Language :: Python :: 3.12
Requires-Dist: typing-extensions (>=4.11.0,<5.0.0)
Project-URL: Repository, https://github.com/jhok2013/pythonix
